llama_index/embeddings/llm_rails/__init__.py
llama_index/embeddings/llm_rails/base.py
llama_index_embeddings_llm_rails-0.4.1.dist-info/METADATA
llama_index_embeddings_llm_rails-0.4.1.dist-info/WHEEL
llama_index_embeddings_llm_rails-0.4.1.dist-info/licenses/LICENSE
llama_index_embeddings_llm_rails-0.4.1.dist-info/RECORD
